jobmaster/__init__.py
jobmaster/decorator.py
jobmaster/deploy.py
jobmaster/jobs.py
jobmaster/tasks.py
jobmaster/utils.py
jobmaster-0.1.1.dist-info/LICENCE
jobmaster-0.1.1.dist-info/METADATA
jobmaster-0.1.1.dist-info/WHEEL
jobmaster-0.1.1.dist-info/top_level.txt
jobmaster-0.1.1.dist-info/RECORD
