Metadata-Version: 2.1
Name: jobmaster
Version: 0.1.1
Summary: JobMaster allows a user to quickly and simply deploy and manage a collection of tasks.
Home-page: https://github.com/DrPrettyman/jobmaster
Author: DrPrettyman
Author-email: joshua@blinkseo.co.uk
License: MIT
Classifier: Intended Audience :: Developers
Classifier: Development Status :: 1 - Planning
Classifier: License :: OSI Approved :: MIT License
Classifier: Operating System :: OS Independent
Classifier: Programming Language :: Python
Classifier: Programming Language :: Python :: 3.10
Classifier: Programming Language :: Python :: 3.11
License-File: LICENCE
Requires-Dist: pg8000
Requires-Dist: sqlalchemy
